unbabel_cli/__init__.py
unbabel_cli/main.py
unbabel_cli/utils/delivery_time.py
unbabel_cli/utils/interfaces.py
unbabel_cli/utils/read_events.py
unbabel_cli-0.1.2.dist-info/METADATA
unbabel_cli-0.1.2.dist-info/WHEEL
unbabel_cli-0.1.2.dist-info/entry_points.txt
unbabel_cli-0.1.2.dist-info/RECORD
