Metadata-Version: 2.1
Name: unbabel-cli
Version: 0.1.2
Summary: unbabel cli for application
Author: Victor Carrillo
Author-email: 31296860+VictorCarrDev@users.noreply.github.com
Requires-Python: >=3.12,<4.0
Classifier: Programming Language :: Python :: 3
Classifier: Programming Language :: Python :: 3.12
Requires-Dist: pytest (>=8.0.1,<9.0.0)
Requires-Dist: typer[all] (>=0.9.0,<0.10.0)
